py_secscan/__init__.py
py_secscan/__main__.py
py_secscan/cli.py
py_secscan/process.py
py_secscan/settings.py
py_secscan/stdx.py
py_secscan/modules/__init__.py
py_secscan/modules/builtins/__init__.py
py_secscan/modules/builtins/sbom_vulnerabilities.py
py_secscan/scan/__init__.py
py_secscan/scan/scan.py
py_secscan/scan/parser/__init__.py
py_secscan/scan/parser/base.py
py_secscan/scan/parser/v1/__init__.py
py_secscan/scan/parser/v1/parser.py
py_secscan/scan/parser/v1/pysecscan.schema.json
py_secscan/view/__init__.py
py_secscan/view/view.py
py_secscan/view/webapp.py
py_secscan-1.0.0.dist-info/METADATA
py_secscan-1.0.0.dist-info/WHEEL
py_secscan-1.0.0.dist-info/entry_points.txt
py_secscan-1.0.0.dist-info/top_level.txt
py_secscan-1.0.0.dist-info/RECORD
