Metadata-Version: 2.2
Name: py-secscan
Version: 1.0.0
Summary: PySecScan is the tool that allows you to perform security scans in your Python project through a simple YAML configuration.
Requires-Python: >=3.10
Requires-Dist: cyclonedx-bom>=5.1.2
Requires-Dist: jsonschema>=4.23.0
Requires-Dist: pyyaml>=6.0.2
Requires-Dist: requests>=2.32.3
Requires-Dist: ruff>=0.8.4
Provides-Extra: view
Requires-Dist: streamlit>=1.42.0; extra == "view"
